MANIFEST.in
setup.py
docs/HISTORY.txt
src/dolmen/__init__.py
src/dolmen.app.viewselector.egg-info/PKG-INFO
src/dolmen.app.viewselector.egg-info/SOURCES.txt
src/dolmen.app.viewselector.egg-info/dependency_links.txt
src/dolmen.app.viewselector.egg-info/namespace_packages.txt
src/dolmen.app.viewselector.egg-info/not-zip-safe
src/dolmen.app.viewselector.egg-info/requires.txt
src/dolmen.app.viewselector.egg-info/top_level.txt
src/dolmen/app/__init__.py
src/dolmen/app/viewselector/README.txt
src/dolmen/app/viewselector/__init__.py
src/dolmen/app/viewselector/configure.zcml
src/dolmen/app/viewselector/menu.py
src/dolmen/app/viewselector/select.py
src/dolmen/app/viewselector/views.py
src/dolmen/app/viewselector/tests/__init__.py
src/dolmen/app/viewselector/tests/ftesting.zcml
src/dolmen/app/viewselector/tests/test_package.py