Metadata-Version: 1.0
Name: dolmen.app.viewselector
Version: 0.2.1
Summary: Dolmen Layout/View Selector
Home-page: http://tracker.trollfot.org/
Author: Souheil Chelfouh
Author-email: souheil@chelfouh.com
License: GPL
Download-URL: http://pypi.python.org/pypi/dolmen.app.viewselector
Keywords: Grok Zope3 CMS Dolmen
Platform: Any
Classifier: Development Status :: 4 - Beta
Classifier: Environment :: Web Environment
Classifier: Framework :: Zope3
Classifier: Intended Audience :: Other Audience
Classifier: License :: OSI Approved :: GNU General Public License (GPL)
Classifier: Operating System :: OS Independent
Classifier: Programming Language :: Python
